{
  "name": "replace_file_content",
  "args": {
    "AllowMultiple": "false",
    "Description": "\"Add search to NoticesView\"",
    "EndLine": "1520",
    "Instruction": "\"Add search state and input for NoticesView. Filter notices by title, body, or audience, and display no matching notices message.\"",
    "ReplacementContent": "\"function NoticesView() {\\n  const [notices, setNotices] = useState([])\\n  const [loading, setLoading] = useState(true)\\n  const [form, setForm] = useState({ title: '', body: '', priority: 'info', audience: 'All teachers' })\\n  const [saving, setSaving] = useState(false)\\n  const [err, setErr] = useState('')\\n  const [search, setSearch] = useState('')\\n\\n  const AUDIENCES = ['All teachers', 'Class teachers', 'All staff']\\n  const PRIORITIES = [\\n    { value: 'info', label: 'Info', color: C.blue },\\n    { value: 'reminder', label: 'Reminder', color: C.yellow },\\n    { value: 'urgent', label: 'Urgent', color: C.red },\\n  ]\\n\\n  const load = useCallback(() => {\\n    setLoading(true)\\n    noticesApi.list()\\n      .then(r => setNotices(r.data.data || []))\\n      .catch(console.error)\\n      .finally(() => setLoading(false))\\n  }, [])\\n\\n  useEffect(() => { load() }, [load])\\n\\n  const sendNotice = async () => {\\n    if (!form.title.trim()) { setErr('Title is required'); return }\\n    setSaving(true); setErr('')\\n    try {\\n      await noticesApi.create(form)\\n      setForm({ title: '', body: '', priority: 'info', audience: 'All teachers' })\\n      load()\\n    } catch (e) { setErr(e.response?.data?.message || 'Failed to send') }\\n    finally { setSaving(false) }\\n  }\\n\\n  const remove = async (id) => {\\n    try { await noticesApi.remove(id); load() }\\n    catch (e) { alert(e.response?.data?.message || 'Failed') }\\n  }\\n\\n  const priorityColor = (p) => PRIORITIES.find(x => x.value === p)?.color || C.muted\\n  const timeAgo = (dateStr) => {\\n    const diff = Date.now() - new Date(dateStr).getTime()\\n    const m = Math.floor(diff / 60000)\\n    if (m < 60) return `${m}m ago`\\n    const h = Math.floor(m / 60)\\n    if (h < 24) return `${h}h ago`\\n    return `${Math.floor(h / 24)}d ago`\\n  }\\n\\n  const filteredNotices = notices.filter(n => {\\n    const q = search.toLowerCase()\\n    return (\\n      (n.title || '').toLowerCase().includes(q) ||\\n      (n.body || '').toLowerCase().includes(q) ||\\n      (n.audience || '').toLowerCa\n<truncated 5267 bytes>",
    "StartLine": "1417",
    "TargetContent": "\"function NoticesView() {\\n  const [notices, setNotices] = useState([])\\n  const [loading, setLoading] = useState(true)\\n  const [form, setForm] = useState({ title: '', body: '', priority: 'info', audience: 'All teachers' })\\n  const [saving, setSaving] = useState(false)\\n  const [err, setErr] = useState('')\\n\\n  const AUDIENCES = ['All teachers', 'Class teachers', 'All staff']\\n  const PRIORITIES = [\\n    { value: 'info', label: 'Info', color: C.blue },\\n    { value: 'reminder', label: 'Reminder', color: C.yellow },\\n    { value: 'urgent', label: 'Urgent', color: C.red },\\n  ]\\n\\n  const load = useCallback(() => {\\n    setLoading(true)\\n    noticesApi.list()\\n      .then(r => setNotices(r.data.data || []))\\n      .catch(console.error)\\n      .finally(() => setLoading(false))\\n  }, [])\\n\\n  useEffect(() => { load() }, [load])\\n\\n  const sendNotice = async () => {\\n    if (!form.title.trim()) { setErr('Title is required'); return }\\n    setSaving(true); setErr('')\\n    try {\\n      await noticesApi.create(form)\\n      setForm({ title: '', body: '', priority: 'info', audience: 'All teachers' })\\n      load()\\n    } catch (e) { setErr(e.response?.data?.message || 'Failed to send') }\\n    finally { setSaving(false) }\\n  }\\n\\n  const remove = async (id) => {\\n    try { await noticesApi.remove(id); load() }\\n    catch (e) { alert(e.response?.data?.message || 'Failed') }\\n  }\\n\\n  const priorityColor = (p) => PRIORITIES.find(x => x.value === p)?.color || C.muted\\n  const timeAgo = (dateStr) => {\\n    const diff = Date.now() - new Date(dateStr).getTime()\\n    const m = Math.floor(diff / 60000)\\n    if (m < 60) return `${m}m ago`\\n    const h = Math.floor(m / 60)\\n    if (h < 24) return `${h}h ago`\\n    return `${Math.floor(h / 24)}d ago`\\n  }\\n\\n  return (\\n    <PageShell title=\\\"Notices & announcements\\\" breadcrumbs=\\\"Branch\\\"\\n      actions={<Pill color={C.green}>Teachers see these in the mobile app</Pill>}>\\n      <div style={{ display: 'grid', gridTemplateColumns: '2fr 1fr', gap: 16 }}>\\n        <div style={{ display\n<truncated 4384 bytes>",
    "TargetFile": "\"/Users/shubhamjain/Documents/Kamlesh/Sikshalaya/src/pages/PrincipalAdmin.jsx\"",
    "toolAction": "\"Adding search to NoticesView\"",
    "toolSummary": "\"Add search in NoticesView\""
  }
}